subcortex_visualization/__init__.py
subcortex_visualization/plotting.py
subcortex_visualization/segmentation.py
subcortex_visualization/utils.py
subcortex_visualization/atlases/AICHA_subcortex.nii.gz
subcortex_visualization/atlases/AICHA_subcortex_lookup.csv
subcortex_visualization/atlases/Brainnetome_subcortex.nii.gz
subcortex_visualization/atlases/Brainnetome_subcortex_lookup.csv
subcortex_visualization/atlases/Melbourne_S1_subcortex.nii.gz
subcortex_visualization/atlases/Melbourne_S1_subcortex_lookup.csv
subcortex_visualization/atlases/Melbourne_S2_subcortex.nii.gz
subcortex_visualization/atlases/Melbourne_S2_subcortex_lookup.csv
subcortex_visualization/atlases/Melbourne_S3_subcortex.nii.gz
subcortex_visualization/atlases/Melbourne_S3_subcortex_lookup.csv
subcortex_visualization/atlases/Melbourne_S4_subcortex.nii.gz
subcortex_visualization/atlases/Melbourne_S4_subcortex_lookup.csv
subcortex_visualization/atlases/SUIT_cerebellar_lobule.nii.gz
subcortex_visualization/atlases/SUIT_cerebellar_lobule_lookup.csv
subcortex_visualization/atlases/Thalamus_Nuclei_HCP.nii.gz
subcortex_visualization/atlases/Thalamus_Nuclei_HCP_lookup.csv
subcortex_visualization/atlases/__init__.py
subcortex_visualization/atlases/aseg_subcortex.nii.gz
subcortex_visualization/atlases/aseg_subcortex_lookup.csv
subcortex_visualization/data/AICHA_L.svg
subcortex_visualization/data/AICHA_L_ordering.csv
subcortex_visualization/data/AICHA_R.svg
subcortex_visualization/data/AICHA_R_ordering.csv
subcortex_visualization/data/AICHA_both.svg
subcortex_visualization/data/AICHA_both_ordering.csv
subcortex_visualization/data/Brainnetome_L.svg
subcortex_visualization/data/Brainnetome_L_ordering.csv
subcortex_visualization/data/Brainnetome_R.svg
subcortex_visualization/data/Brainnetome_R_ordering.csv
subcortex_visualization/data/Brainnetome_both.svg
subcortex_visualization/data/Brainnetome_both_ordering.csv
subcortex_visualization/data/Melbourne_S1_L.svg
subcortex_visualization-1.2.0.dist-info/licenses/LICENSE.txt
subcortex_visualization-1.2.0.dist-info/METADATA
subcortex_visualization-1.2.0.dist-info/WHEEL
subcortex_visualization-1.2.0.dist-info/top_level.txt
subcortex_visualization-1.2.0.dist-info/RECORD
