Metadata-Version: 2.4
Name: subcortex_visualization
Version: 1.2.0
Summary: A package to visualize subcortical and cerebellar brain data in two dimensions.
Author: Annie G. Bryant
Author-email: "Annie G. Bryant" <anniegbryant@gmail.com>
License: GNU General Public License v3 (GPLv3)
Project-URL: Homepage, https://github.com/anniegbryant/subcortex_visualization
Project-URL: Issues, https://github.com/anniegbryant/subcortex_visualization/issues
Classifier: Programming Language :: Python
Classifier: Programming Language :: Python :: 3
Classifier: Development Status :: 1 - Planning
Classifier: Operating System :: OS Independent
Classifier: Intended Audience :: Science/Research
Classifier: Environment :: Console
Classifier: Environment :: Other Environment
Classifier: Topic :: Scientific/Engineering :: Bio-Informatics
Classifier: Topic :: Scientific/Engineering :: Information Analysis
Classifier: Topic :: Scientific/Engineering :: Medical Science Apps.
Requires-Python: >=3.9
License-File: LICENSE.txt
Dynamic: author
Dynamic: license-file
